verse/ai/audio_embedding/__init__.py
verse/ai/audio_embedding/_operation.py
verse/ai/audio_embedding/_operation_parser.py
verse/ai/audio_embedding/component.py
verse/ai/audio_embedding/providers/clap.py
verse/ai/audio_embedding/providers/default.py
verse/ai/audio_embedding/providers/hosted.py
verse/ai/audio_embedding/py.typed
verse/ai/chat_completion/__init__.py
verse/ai/chat_completion/_helper.py
verse/ai/chat_completion/_models.py
verse/ai/chat_completion/_operation.py
verse/ai/chat_completion/_operation_parser.py
verse/ai/chat_completion/component.py
verse/ai/chat_completion/providers/anthropic.py
verse/ai/chat_completion/providers/cohere.py
verse/ai/chat_completion/providers/default.py
verse/ai/chat_completion/providers/hosted.py
verse/ai/chat_completion/providers/openai.py
verse/ai/chat_completion/py.typed
verse/ai/image_captioning/__init__.py
verse/ai/image_captioning/_operation.py
verse/ai/image_captioning/_operation_parser.py
verse/ai/image_captioning/component.py
verse/ai/image_captioning/providers/blip.py
verse/ai/image_captioning/providers/chat_completion_provider.py
verse/ai/image_captioning/providers/default.py
verse/ai/image_captioning/providers/hosted.py
verse/ai/image_captioning/py.typed
verse/ai/image_embedding/__init__.py
verse/ai/image_embedding/_operation.py
verse/ai/image_embedding/_operation_parser.py
verse/ai/image_embedding/component.py
verse/ai/image_embedding/providers/clip.py
verse/ai/image_embedding/providers/default.py
verse/ai/image_embedding/providers/hosted.py
verse/ai/image_embedding/providers/local.py
verse/ai/image_embedding/py.typed
verse/ai/image_generation/__init__.py
verse/ai/image_generation/_models.py
verse/ai/image_generation/component.py
verse/ai/image_generation/providers/hyperbolic.py
verse/ai/speech_recognition/__init__.py
verse/ai/speech_recognition/_models.py
verse/ai/speech_recognition/_operation.py
verse/ai/speech_recognition/_operation_parser.py
verse/ai/speech_recognition/component.py
verse_ai-0.0.22.dist-info/LICENSE
verse_ai-0.0.22.dist-info/METADATA
verse_ai-0.0.22.dist-info/WHEEL
verse_ai-0.0.22.dist-info/RECORD
