Metadata-Version: 2.3
Name: verse-ai
Version: 0.0.22
Summary: Verse AI Components
License: MIT
Keywords: verse,ai,components
Author: Verse
Author-email: admin@rapidverse.com
Requires-Python: >=3.9
Classifier: License :: OSI Approved :: MIT License
Classifier: Programming Language :: Python :: 3
Classifier: Programming Language :: Python :: 3.9
Classifier: Programming Language :: Python :: 3.10
Classifier: Programming Language :: Python :: 3.11
Classifier: Programming Language :: Python :: 3.12
Classifier: Programming Language :: Python :: 3.13
Provides-Extra: all
Provides-Extra: chat-completion-cohere
Provides-Extra: chat-completion-default
Provides-Extra: chat-completion-hosted
Provides-Extra: chat-completion-openai
Provides-Extra: image-captioning-blip
Provides-Extra: image-captioning-chat-completion-provider
Provides-Extra: image-captioning-default
Provides-Extra: image-captioning-hosted
Provides-Extra: image-embedding-clip
Provides-Extra: image-embedding-default
Provides-Extra: image-embedding-hosted
Provides-Extra: speech-recognition-azure-speech
Provides-Extra: speech-recognition-default
Provides-Extra: speech-recognition-google-speech-to-text
Provides-Extra: speech-recognition-hosted
Provides-Extra: speech-recognition-whisper
Provides-Extra: text-to-speech-default
Provides-Extra: text-to-speech-hyberbolic
Provides-Extra: zero-shot-image-classification-clip
Provides-Extra: zero-shot-image-classification-default
Provides-Extra: zero-shot-image-classification-hosted
Requires-Dist: av ; extra == "all"
Requires-Dist: azure-cognitiveservices-speech ; extra == "speech-recognition-azure-speech" or extra == "all"
Requires-Dist: cohere ; extra == "chat-completion-cohere" or extra == "all"
Requires-Dist: google-cloud-speech ; extra == "speech-recognition-google-speech-to-text" or extra == "all"
Requires-Dist: httpx ; extra == "chat-completion-hosted" or extra == "image-captioning-hosted" or extra == "image-embedding-hosted" or extra == "speech-recognition-hosted" or extra == "zero-shot-image-classification-hosted" or extra == "text-to-speech-hyberbolic" or extra == "all"
Requires-Dist: munch ; extra == "text-to-speech-default"
Requires-Dist: numpy (<2) ; extra == "image-captioning-blip" or extra == "image-captioning-default" or extra == "image-embedding-clip" or extra == "image-embedding-default" or extra == "zero-shot-image-classification-clip" or extra == "zero-shot-image-classification-default" or extra == "all"
Requires-Dist: openai ; extra == "chat-completion-openai" or extra == "chat-completion-default" or extra == "all"
Requires-Dist: openai-whisper ; extra == "speech-recognition-whisper" or extra == "speech-recognition-default" or extra == "all"
Requires-Dist: phonemizer ; extra == "text-to-speech-default"
Requires-Dist: scipy ; extra == "text-to-speech-default"
Requires-Dist: torch ; extra == "image-captioning-blip" or extra == "image-captioning-default" or extra == "image-embedding-clip" or extra == "image-embedding-default" or extra == "zero-shot-image-classification-clip" or extra == "zero-shot-image-classification-default" or extra == "text-to-speech-default" or extra == "all"
Requires-Dist: transformers ; extra == "image-captioning-blip" or extra == "image-captioning-default" or extra == "image-embedding-clip" or extra == "image-embedding-default" or extra == "zero-shot-image-classification-clip" or extra == "zero-shot-image-classification-default" or extra == "text-to-speech-default" or extra == "all"
Project-URL: Documentation, https://github.com/rapidverse/verse
Project-URL: Homepage, https://github.com/rapidverse/verse
Project-URL: Repository, https://github.com/rapidverse/verse
